csh_lambda_decorators/__init__.py
csh_lambda_decorators/logging.py
csh_lambda_decorators/stream_event_parsers.py
csh_lambda_decorators/streams.py
comapsmarthome_lambda_decorators-1.5.0.dist-info/METADATA
comapsmarthome_lambda_decorators-1.5.0.dist-info/WHEEL
comapsmarthome_lambda_decorators-1.5.0.dist-info/top_level.txt
comapsmarthome_lambda_decorators-1.5.0.dist-info/RECORD
