Metadata-Version: 2.1
Name: comapsmarthome-lambda-decorators
Version: 1.5.0
Summary: Helpful decorators for aws lambda handler functions
Home-page: 
Author: Aurélien Sylvan
Author-email: aurelien.sylvan@comap.eu
Classifier: Programming Language :: Python :: 3
Classifier: License :: OSI Approved :: MIT License
Classifier: Operating System :: OS Independent
Requires-Dist: simplejson (>=3.17.6)
